{
  "spacing-inset-2xs": {
    "$type": "number",
    "$value": 4,
    "$extensions": {
      "com.figma.variableId": "VariableID:4292:714",
      "com.figma.scopes": [
        "ALL_SCOPES"
      ],
      "com.figma.isOverride": true
    }
  },
  "spacing-inset-xs": {
    "$type": "number",
    "$value": 8,
    "$extensions": {
      "com.figma.variableId": "VariableID:4292:715",
      "com.figma.scopes": [
        "ALL_SCOPES"
      ],
      "com.figma.isOverride": true
    }
  },
  "spacing-inset-sm": {
    "$type": "number",
    "$value": 12,
    "$extensions": {
      "com.figma.variableId": "VariableID:4292:716",
      "com.figma.scopes": [
        "ALL_SCOPES"
      ],
      "com.figma.isOverride": true
    }
  },
  "spacing-inset-md": {
    "$type": "number",
    "$value": 16,
    "$extensions": {
      "com.figma.variableId": "VariableID:4292:717",
      "com.figma.scopes": [
        "ALL_SCOPES"
      ],
      "com.figma.isOverride": true
    }
  },
  "spacing-inset-lg": {
    "$type": "number",
    "$value": 24,
    "$extensions": {
      "com.figma.variableId": "VariableID:4292:718",
      "com.figma.scopes": [
        "ALL_SCOPES"
      ],
      "com.figma.isOverride": true
    }
  },
  "spacing-inset-xl": {
    "$type": "number",
    "$value": 32,
    "$extensions": {
      "com.figma.variableId": "VariableID:4292:719",
      "com.figma.scopes": [
        "ALL_SCOPES"
      ],
      "com.figma.isOverride": true
    }
  },
  "spacing-inset-2xl": {
    "$type": "number",
    "$value": 40,
    "$extensions": {
      "com.figma.variableId": "VariableID:4292:720",
      "com.figma.scopes": [
        "ALL_SCOPES"
      ],
      "com.figma.isOverride": true
    }
  },
  "$extensions": {
    "com.figma.modeName": "Mode 1"
  }
}